{"type":"FeatureCollection","features":[{"type":"Feature","properties":{"marker-color":"#1d7e16","marker-size":"medium","marker-symbol":"wetland","Placename":"Semiahmoo Bay (Blackie Spit)","notes":"\"Boundary Bay, Canada's top bird area, is a major stop-over on the Pacific Flyway\"","link":"https://www.birdsonthebay.ca/botb.html","Contributor":"Luke Bergmann"},"geometry":{"type":"Point","coordinates":[-122.87710189819335,49.0620569455363]}},{"type":"Feature","properties":{"marker-color":"#e90018","marker-size":"medium","marker-symbol":"star-stroked","Placename":"Richmond Night Market!","notes":"Food, shopping, entertainment... summer weekend nights...","link":"https://richmondnightmarket.com/","Contributor":"Luke Bergmann"},"geometry":{"type":"Point","coordinates":[-123.13214242458344,49.19434277016657]}}]}